{
  "name": "Embodied Intelligence",
  "filename": "embodied-intelligence",
  "aliases": [],
  "category": "cognitive",
  "context": "Intelligence that emerges from interaction with physical or virtual environments; central to understanding both biological and artificial minds.",
  "sources": [
    "knowledge_base/papers/edited/AI: A Bridge Toward Diverse Intelligence_edited.md"
  ],
  "is_new": true,
  "_metadata": {
    "entity_type": "concept",
    "last_updated": "2025-10-20T19:55:58.762788",
    "sources_count": 1,
    "contexts_count": 1
  }
}