{
  "name": "Resonance",
  "filename": "resonance",
  "aliases": [
    "vibrational interaction",
    "synchrony",
    "oscillatory coupling",
    "wave patterns"
  ],
  "sources": [
    "batched_extraction"
  ],
  "context": "Self-reinforcing pattern of interaction between elements of thought",
  "category": "interdisciplinary",
  "is_new": false,
  "_metadata": {
    "entity_type": "concept",
    "last_updated": "2025-10-20T21:55:32.071780",
    "sources_count": 1,
    "contexts_count": 1
  }
}