{
  "name": "",
  "filename": "how-can-consciousness-be-understood-as-a-continuum",
  "aliases": [],
  "sources": [],
  "context": "Central to reconceptualizing consciousness across biological scales from single cells to organisms.",
  "question": "How can consciousness be understood as a continuum rather than a binary property?",
  "category": "metaphysics",
  "is_new": true,
  "_metadata": {
    "entity_type": "question",
    "last_updated": "2025-10-20T21:21:25.290681",
    "sources_count": 0,
    "contexts_count": 1
  }
}