{
  "name": "",
  "filename": "what-are-the-minimal-physical-requirements-for-consciousness",
  "aliases": [],
  "sources": [],
  "context": "TAME suggests causal structure and cybernetic properties matter more than substrate; challenges finding true zero on consciousness scale",
  "question": "What are the minimal physical requirements for consciousness to exist?",
  "category": "metaphysics",
  "is_new": true,
  "_metadata": {
    "entity_type": "question",
    "last_updated": "2025-10-20T20:57:54.291875",
    "sources_count": 0,
    "contexts_count": 1
  }
}