{
  "name": "Cellular Collective Intelligence Research Program",
  "filename": "cellular-collective-intelligence-research-program",
  "aliases": [],
  "sources": [
    "knowledge_base/papers/edited/AI: A Bridge Toward Diverse Intelligence_edited.md"
  ],
  "context": "Interdisciplinary investigation spanning philosophy of mind, evolution, and regenerative medicine to understand problem-solving in non-neural biological systems.",
  "creator": [
    "Michael Levin"
  ],
  "is_new": true,
  "_metadata": {
    "entity_type": "framework",
    "last_updated": "2025-10-20T20:57:54.259497",
    "sources_count": 1,
    "contexts_count": 1
  }
}